qfast/native/sc.py
qfast_sc-1.0.1.dist-info/LICENSE.txt
qfast_sc-1.0.1.dist-info/METADATA
qfast_sc-1.0.1.dist-info/WHEEL
qfast_sc-1.0.1.dist-info/top_level.txt
qfast_sc-1.0.1.dist-info/RECORD
