Metadata-Version: 2.1
Name: qfast-sc
Version: 1.0.1
Summary: QFAST SearchCompiler Plugin
Home-page: https://github.com/edyounis/qfast-sc
Author: Ed Younis
Author-email: edyounis@berkeley.edu
License: UNKNOWN
Project-URL: Bug Tracker, https://github.com/edyounis/qfast-sc/issues
Project-URL: Source Code, https://github.com/edyounis/qfast-sc
Keywords: quantum synthesis compilation
Platform: UNKNOWN
Classifier: Development Status :: 2 - Pre-Alpha
Classifier: Environment :: Console
Classifier: Intended Audience :: Developers
Classifier: Intended Audience :: Science/Research
Classifier: Operating System :: OS Independent
Classifier: Programming Language :: Other Scripting Engines
Classifier: Programming Language :: Python :: 3 :: Only
Classifier: Programming Language :: Python :: 3.5
Classifier: Programming Language :: Python :: 3.6
Classifier: Programming Language :: Python :: 3.7
Classifier: Topic :: Scientific/Engineering
Classifier: Topic :: Scientific/Engineering :: Mathematics
Classifier: Topic :: Scientific/Engineering :: Physics
Classifier: Topic :: Software Development :: Compilers
Requires-Python: >=3.5, <4
Requires-Dist: qfast (>=1.0.0)
Requires-Dist: search-compiler (>=1.2.0)
